setup.cfg
setup.py
brain/__init__.py
brain/brain_py2.py
brain/brain_py3.py
pythonbrain.egg-info/PKG-INFO
pythonbrain.egg-info/SOURCES.txt
pythonbrain.egg-info/dependency_links.txt
pythonbrain.egg-info/top_level.txt
pythonbrain.egg-info/zip-safe