Metadata-Version: 1.1
Name: pythonbrain
Version: 0.4.2
Summary: lightweight neural network library for Python
Home-page: http://github.com/jrialland/python-brain
Author: Julien Rialland
Author-email: julien.rialland@gmail.com
License: Apache License 2.0
Download-URL: https://github.com/jrialland/python-brain/tarball/0.4.2
Keywords: ia,neural network
Platform: UNKNOWN
Classifier: Intended Audience :: Developers
Classifier: Operating System :: OS Independent
Classifier: Topic :: Software Development
Classifier: Topic :: Scientific/Engineering :: Artificial Intelligence
Classifier: Programming Language :: Python
Classifier: Programming Language :: Python :: 2
Classifier: Programming Language :: Python :: 3
Provides: brain
